oscar_iyzipay/oscar_iyzipay/__init__.py
oscar_iyzipay/oscar_iyzipay/admin.py
oscar_iyzipay/oscar_iyzipay/apps.py
oscar_iyzipay/oscar_iyzipay/migrations/__init__.py
oscar_iyzipay/oscar_iyzipay/models.py
oscar_iyzipay/oscar_iyzipay/tests.py
oscar_iyzipay/oscar_iyzipay/urls.py
oscar_iyzipay/oscar_iyzipay/views.py
oscar_iyzipay/templates/oscar/checkout/failure.html
oscar_iyzipay/templates/oscar/checkout/get.html
oscar_iyzipay/templates/oscar/checkout/post.html
django_oscar_iyzipay-1.0.4.dist-info/LICENSE
django_oscar_iyzipay-1.0.4.dist-info/METADATA
django_oscar_iyzipay-1.0.4.dist-info/WHEEL
django_oscar_iyzipay-1.0.4.dist-info/RECORD
