Metadata-Version: 2.1
Name: django-oscar-iyzipay
Version: 1.0.4
Summary: Integration between django-oscar and iyzipay
Home-page: https://github.com/bahadirozkan/django-oscar-iyzipay
Author: Bahadır Özkan
Author-email: bahadirozkan@gmail.com
Requires-Python: >=3.9,<3.10
Classifier: Programming Language :: Python :: 3
Classifier: Programming Language :: Python :: 3.9
Requires-Dist: django-ipware (>=6.0.3,<7.0.0)
Requires-Dist: django-oscar (<=3.1)
Requires-Dist: iyzipay (>=1.0.41,<2.0.0)
Requires-Dist: pre-commit (>=3.6.2,<4.0.0)
Requires-Dist: ujson (>=5.9.0,<6.0.0)
